diceware/__about__.py
diceware/__init__.py
diceware/__main__.py
diceware/config.py
diceware/logger.py
diceware/random_sources.py
diceware/wordlist.py
diceware/wordlists/wordlist_ca.txt
diceware/wordlists/wordlist_de.txt
diceware/wordlists/wordlist_de_8k.txt
diceware/wordlists/wordlist_en_adjectives.txt
diceware/wordlists/wordlist_en_eff.txt
diceware/wordlists/wordlist_en_nouns.txt
diceware/wordlists/wordlist_en_securedrop.asc
diceware/wordlists/wordlist_es.txt
diceware/wordlists/wordlist_fr.txt
diceware/wordlists/wordlist_it.txt
diceware/wordlists/wordlist_pt-br.txt
diceware-1.0.dist-info/LICENSE
diceware-1.0.dist-info/METADATA
diceware-1.0.dist-info/WHEEL
diceware-1.0.dist-info/entry_points.txt
diceware-1.0.dist-info/top_level.txt
diceware-1.0.dist-info/RECORD
